astrotime/__init__.py
astrotime/config/__init__.py
astrotime/config/context.py
astrotime/encoders/__init__.py
astrotime/encoders/base.py
astrotime/encoders/baseline.py
astrotime/encoders/corentropy.py
astrotime/encoders/correlation.py
astrotime/encoders/embedding.py
astrotime/encoders/expansion.py
astrotime/encoders/folding.py
astrotime/encoders/gls.py
astrotime/encoders/octaves.py
astrotime/encoders/polynomial.py
astrotime/encoders/spectral.py
astrotime/encoders/spectral_autocorr.py
astrotime/encoders/spectral_autocorr1.py
astrotime/encoders/wavelet.py
astrotime/encoders/spline/__init__.py
astrotime/encoders/spline/interpolate.py
astrotime/encoders/spline/misc.py
astrotime/encoders/wotan/__init__.py
astrotime/encoders/wotan/detrend.py
astrotime/encoders/wotan/flatten.py
astrotime/loaders/MIT.py
astrotime/loaders/__init__.py
astrotime/loaders/base.py
astrotime/loaders/pcross.py
astrotime/loaders/sinusoid.py
astrotime/loaders/synthetic.py
astrotime/loaders/wwz.py
astrotime/models/__init__.py
astrotime/models/cnn/__init__.py
astrotime/models/cnn/cnn_baseline.py
astrotime/models/kernel/__init__.py
astrotime/models/kernel/gaussian_process.py
astrotime/models/kernel/spectral_mixture.py
astrotime/models/kernel/util.py
astrotime/models/spectral/__init__.py
astrotime/models/spectral/peak_finder.py
astrotime/models/transformer/__init__.py
astrotime/models/transformer/attention.py
astrotime/models/transformer/model.py
astrotime/models/transformer/trainer.py
astrotime/models/unet/__init__.py
astrotime/models/unet/hdemucs.py
astrotime/plot/MIT_synthetic.py
astrotime/plot/__init__.py
astrotime/plot/analysis.py
astrotime/plot/base.py
astrotime/plot/data.py
astrotime/plot/functions.py
astrotime/plot/param.py
astrotime/plot/snr.py
astrotime/plot/transform.py
astrotime/plot/widgets.py
astrotime/trainers/__init__.py
astrotime/trainers/checkpoints.py
astrotime/trainers/filters.py
astrotime/trainers/iterative_trainer.py
astrotime/trainers/loss.py
astrotime/trainers/model_evaluator.py
astrotime-0.0.1.dist-info/METADATA
astrotime-0.0.1.dist-info/WHEEL
astrotime-0.0.1.dist-info/top_level.txt
astrotime-0.0.1.dist-info/zip-safe
astrotime-0.0.1.dist-info/RECORD
