Metadata-Version: 2.4
Name: astrotime
Version: 0.0.1
Summary: Methods for pytorch deep learning applications
Home-page: https://github.com/nasa-nccs-hpda/astrotime
Author: jordancaraballo
Author-email: jordan.a.caraballo-vega@nasa.gov
License: MIT
Project-URL: Documentation, https://github.com/nasa-nccs-hpda/astrotime
Project-URL: Source, https://github.com/nasa-nccs-hpda/astrotime
Project-URL: Issues, https://github.com/nasa-nccs-hpda/astrotime/issues
Keywords: astrotime,deep-learning,machine-learning
Classifier: Development Status :: 4 - Beta
Classifier: Intended Audience :: Developers
Classifier: Intended Audience :: Science/Research
Classifier: Topic :: Software Development :: Libraries :: Python Modules
Classifier: License :: OSI Approved :: MIT License
Classifier: Programming Language :: Python :: 3 :: Only
Requires-Python: >=3.10
Requires-Dist: omegaconf
Requires-Dist: tqdm
Requires-Dist: transformers
Requires-Dist: datasets
Requires-Dist: webdataset
Requires-Dist: deepspeed
Requires-Dist: huggingface_hub[cli,torch]
Requires-Dist: scipy
Requires-Dist: astropy
Requires-Dist: lightkurve
Requires-Dist: fitsio
Requires-Dist: scikit-learn
Requires-Dist: pandas
Requires-Dist: numpy
Requires-Dist: tqdm
Requires-Dist: rtree
Requires-Dist: diskcache
Requires-Dist: ninja
Requires-Dist: xarray
Requires-Dist: netCDF4
Requires-Dist: torchcde
Requires-Dist: torchdiffeq
Requires-Dist: hydra-core
Requires-Dist: rich
Requires-Dist: timm
Requires-Dist: supervision
Requires-Dist: pytest
Requires-Dist: coveralls
Provides-Extra: test
Requires-Dist: pytest; extra == "test"
Requires-Dist: coverage[toml]; extra == "test"
Requires-Dist: black; extra == "test"
Provides-Extra: docs
Requires-Dist: pdoc==8.0.1; extra == "docs"
Provides-Extra: all
Requires-Dist: pdoc==8.0.1; extra == "all"
Requires-Dist: pytest; extra == "all"
Requires-Dist: coverage[toml]; extra == "all"
Requires-Dist: black; extra == "all"
